greenscale_ai/__init__.py
greenscale_ai/greenscale_ai.py
greenscale_ai-0.1.2.dist-info/LICENSE
greenscale_ai-0.1.2.dist-info/METADATA
greenscale_ai-0.1.2.dist-info/WHEEL
greenscale_ai-0.1.2.dist-info/top_level.txt
greenscale_ai-0.1.2.dist-info/RECORD
