Metadata-Version: 2.1
Name: greenscale-ai
Version: 0.1.2
Summary: Python SDK for Greenscale AI
Home-page: https://github.com/greenscale-ai/greenscale-ai-sdk
Author: Greenscale AI
Author-email: hello@greenscale.ai
Classifier: Programming Language :: Python :: 3
Classifier: License :: OSI Approved :: MIT License
Classifier: Operating System :: OS Independent
Requires-Python: >=3.6
License-File: LICENSE
Requires-Dist: requests>=2.25.0
